{"type": "Feature", "properties": {"type": "node", "id": 268401565, "tags": {"amenity": "drinking_water", "check_date": "2022-09-07", "fountain": "drinking", "historic": "yes", "name": "Fontana dell'Aquila", "wheelchair": "limited", "wikidata": "Q3747377", "wikipedia": "it:Fontana dell'aquila (Trento)"}}, "geometry": {"type": "Point", "coordinates": [11.1215698, 46.0677293]}}