{"type": "Feature", "properties": {"type": "node", "id": 469206794, "tags": {"amenity": "drinking_water", "name": "Fontana del Gai"}}, "geometry": {"type": "Point", "coordinates": [11.1804149, 46.0428286]}}