{"type": "Feature", "properties": {"type": "node", "id": 2925010847, "tags": {"amenity": "bicycle_rental", "capacity": "12", "name": "e.motion / Stazione FS - Ospedale", "network": "E.Motion", "operator": "Provincia di Trento", "website": "http://www.provincia.tn.it/bikesharing"}}, "geometry": {"type": "Point", "coordinates": [11.1355363, 46.0544437]}}