{"type": "Feature", "properties": {"type": "node", "id": 6816067336, "tags": {"amenity": "bicycle_rental", "capacity": "6", "name": "e.motion / Centro Intermodale", "network": "E.Motion", "operator": "Provincia Autonoma di Trento"}}, "geometry": {"type": "Point", "coordinates": [11.2325588, 46.0626989]}}