{"type": "Feature", "properties": {"type": "node", "id": 3952792104, "tags": {"amenity": "bicycle_rental", "capacity": "6", "name": "e.motion / Spiaz de le Oche", "network": "E.Motion", "operator": "Provincia Autonoma di Trento"}}, "geometry": {"type": "Point", "coordinates": [11.2390585, 46.0587731]}}